qnm/LICENSE
qnm/__init__.py
qnm/_version.py
qnm/angular.py
qnm/cached.py
qnm/contfrac.py
qnm/nearby.py
qnm/radial.py
qnm/spinsequence.py
qnm/schwarzschild/__init__.py
qnm/schwarzschild/approx.py
qnm/schwarzschild/overtonesequence.py
qnm/schwarzschild/tabulated.py
qnm/schwarzschild/data/Schw_dict.pickle
qnm-0.4.4.dist-info/LICENSE
qnm-0.4.4.dist-info/METADATA
qnm-0.4.4.dist-info/WHEEL
qnm-0.4.4.dist-info/pbr.json
qnm-0.4.4.dist-info/top_level.txt
qnm-0.4.4.dist-info/RECORD
