Metadata-Version: 2.1
Name: qnm
Version: 0.4.4
Summary: Package for computing Kerr quasinormal mode frequencies, separation constants, and spherical-spheroidal mixing coefficients
Home-page: https://github.com/duetosymmetry/qnm/
Author: Leo C. Stein
Author-email: leo.stein@gmail.com
Project-URL: Bug Tracker, https://github.com/duetosymmetry/qnm/issues
Project-URL: Documentation, https://qnm.readthedocs.io/
Project-URL: Source Code, https://github.com/duetosymmetry/qnm
Keywords: black holes quasinormal modes physics scientific computing numerical methods
Classifier: Intended Audience :: Science/Research
Classifier: Natural Language :: English
Classifier: Topic :: Scientific/Engineering :: Physics
Classifier: Topic :: Scientific/Engineering :: Astronomy
Classifier: License :: OSI Approved :: MIT License
Classifier: Programming Language :: Python
Classifier: Operating System :: OS Independent
License-File: LICENSE
Requires-Dist: numpy
Requires-Dist: scipy
Requires-Dist: numba
Requires-Dist: tqdm
